<?xml version="1.0" encoding="UTF-8" standalone="yes"?>
<document id="doc0000022" url="http://www.nbcsandiego.com/news/politics/Candidate-Blames-Opponent-for-Attack-105796143.html" time="2012-07-12-15:12" support="8" score="0.016372125125800163" bingtitle="Candidate Blames Opponent for Attack | NBC San Diego" webtitle="Candidate Blames Opponent for Attack  | NBC 7 San Diego">
			<query id="000277" bing-rank="93"/>
			<query id="000279" bing-rank="212"/>
			<query id="000252" bing-rank="162"/>
			<query id="000892" bing-rank="81"/>
			<query id="001361" bing-rank="183"/>
			<query id="000421" bing-rank="154"/>
			<query id="000266" bing-rank="17"/>
			<query id="000270" bing-rank="128"/>
	<description>... attacked while making an early-morning order at a local fast food restaurant ... Sunday at that location but couldn’t confirm ... I’ve exposed the district for the waste of ...</description>
	<body>
		Local Olympics Politics Decision 2012 Sports Health Tech Weird Weather 
 Blogs 
 Prop Zero Press Here U.S.&amp;World 
 
 Celebrity Movies Television Music 
 Blogs 
 PopcornBiz 
 
 Food&amp;Drink Fashion Shopping Events Real Estate San Diego Deals 
 Blogs 
 1st Look Open House SoundDiego Worth the Drive 
 
 As Seen On Shows Contests Community About Us TV Schedule 
 
 Forecast Maps&amp;Radar Severe Weather Alerts Weather Stories 
 
 Today&apos;s Offer Marketplace Contests 
 
 65° 

 76 | 67 
 Submit photos | Tips 
 home news Video Weather Investigations Entertainment The Scene On Air Traffic the goods 
 
 
 
 Local Olympics Politics Decision 2012 Sports Health Tech Weird Weather BLOGS: Prop Zero Press Here U.S.&amp;World 
 home &gt; news &gt; politics 
Candidate Blames Opponent for Attack


 
By R. Stickney and Gene Cubbison 

| Tuesday, Oct 26, 2010 | Updated 12:19 PM PDT
 View Comments ( ) | Email | Print
	</body>
</document>
