<?xml version="1.0" encoding="UTF-8" standalone="yes"?>
<document id="doc0002608" url="http://www.schmap.com/dusseldorf/restaurants_bilk/" time="2012-07-12-18:40" support="5" score="0.011548267531251112" bingtitle="Schmap Dusseldorf Restaurants - Bilk - San Francisco - Real-time ..." webtitle="Dusseldorf - Restaurants - Bilk">
			<query id="000860" bing-rank="149"/>
			<query id="001111" bing-rank="223"/>
			<query id="001268" bing-rank="75"/>
			<query id="000358" bing-rank="196"/>
			<query id="000045" bing-rank="201"/>
	<description>The courtyard makes a particularly enticing place to sit ... is also not a bother to grab a quick bite to eat ... This U.S. style fast-food restaurant might be considered the ...</description>
	<body>
		Places

Photos
 Schmap.com | About | News&amp;Reviews | Privacy | Terms of Use | Contact Us 
Copyright©2009 Schmap, Inc. All rights reserved. Guides Mobile Geotweet Widgets Publish Enable Schmap.me
	</body>
</document>
