<?xml version="1.0" encoding="UTF-8" standalone="yes"?>
<document id="doc0008552" url="http://earningmoneyexplore.info/" time="2012-07-13-02:01" support="12" score="0.013591849270043794" bingtitle="Earning Money Explore" webtitle="T-Online Navigationshilfe">
			<query id="000136" bing-rank="97"/>
			<query id="000149" bing-rank="120"/>
			<query id="000139" bing-rank="109"/>
			<query id="001277" bing-rank="226"/>
			<query id="000135" bing-rank="116"/>
			<query id="000141" bing-rank="68"/>
			<query id="001267" bing-rank="200"/>
			<query id="000154" bing-rank="246"/>
			<query id="000142" bing-rank="227"/>
			<query id="000515" bing-rank="241"/>
			<query id="000151" bing-rank="135"/>
			<query id="000150" bing-rank="206"/>
	<description>... to Crochet Free Crochet Patterns for Napkin ... an advertisement significantly reduces fast-food restaurant advertising exposure on television, and an increase in the number ...</description>
	<body>
		Willkommen bei T-Online

 weiter....
	</body>
</document>
