<?xml version="1.0" encoding="UTF-8" standalone="yes"?>
<document id="doc0009505" url="http://livonia.areaconnect.com/restaurants/" time="2012-07-13-02:53" support="5" score="0.02341065535116385" bingtitle="Livonia Restaurants and Food (Livonia, MI)" webtitle="Livonia Restaurants and Food (Livonia, MI)">
			<query id="000296" bing-rank="147"/>
			<query id="000290" bing-rank="92"/>
			<query id="000310" bing-rank="200"/>
			<query id="000547" bing-rank="223"/>
			<query id="001003" bing-rank="238"/>
	<description>American Table Dining - Map 33501 8 Mile Rd Livonia, MI 48152 ... Enter Restaurant Name:</description>
	<body>
		Livonia Restaurants
 
 Livonia AreaConnect  |  AreaConnect
	</body>
</document>
